awsmate/__init__.py
awsmate/apigateway.py
awsmate/eventbridge.py
awsmate/lambdafunction.py
awsmate/logger.py
awsmate/s3.py
awsmate/sns.py
awsmate-0.4.2.dist-info/METADATA
awsmate-0.4.2.dist-info/WHEEL
awsmate-0.4.2.dist-info/licenses/LICENSE.txt
awsmate-0.4.2.dist-info/RECORD
