Metadata-Version: 2.3
Name: awsmate
Version: 0.4.2
Summary: A companion for your AWS Python developments.
Project-URL: Repository, https://github.com/shlublu/awsmate
Project-URL: Documentation, https://awsmate.readthedocs.io/
Project-URL: Bug Tracker, https://github.com/shlublu/awsmate/issues
Project-URL: Changelog, https://github.com/shlublu/awsmate/blob/master/CHANGELOG.md
Author-email: "Vincent Poulain (Shlublu)" <shlublu@yahoo.fr>
License-File: LICENSE.txt
Keywords: aws,aws-apigateway,aws-eventbridge,aws-lambda,aws-s3,python
Classifier: Development Status :: 4 - Beta
Classifier: Intended Audience :: Developers
Classifier: License :: OSI Approved :: European Union Public Licence 1.2 (EUPL 1.2)
Classifier: Operating System :: OS Independent
Classifier: Programming Language :: Python :: 3.9
Classifier: Programming Language :: Python :: 3.10
Classifier: Programming Language :: Python :: 3.11
Classifier: Programming Language :: Python :: 3.12
Classifier: Topic :: Software Development :: Libraries :: Python Modules
Requires-Python: >=3.8
